pypkgs_jaredejs/__init__.py
pypkgs_jaredejs/pypkgs_jaredejs.py
pypkgs_jaredejs-0.1.0.dist-info/LICENSE
pypkgs_jaredejs-0.1.0.dist-info/WHEEL
pypkgs_jaredejs-0.1.0.dist-info/METADATA
pypkgs_jaredejs-0.1.0.dist-info/RECORD
