Metadata-Version: 2.1
Name: pypkgs-jaredejs
Version: 0.1.0
Summary: Python package for individual assignment 1 in UBC MDS DSCI 524
License: MIT
Author: Your Name
Author-email: you@example.com
Requires-Python: >=3.8,<4.0
Classifier: License :: OSI Approved :: MIT License
Classifier: Programming Language :: Python :: 3
Classifier: Programming Language :: Python :: 3.8
Classifier: Programming Language :: Python :: 3.9
Requires-Dist: pandas (>=1.2.2,<2.0.0)
